godrive/__init__.py
godrive/godrive.py
godrive-1.0.3.dist-info/LICENSE
godrive-1.0.3.dist-info/METADATA
godrive-1.0.3.dist-info/WHEEL
godrive-1.0.3.dist-info/entry_points.txt
godrive-1.0.3.dist-info/top_level.txt
godrive-1.0.3.dist-info/RECORD
