Metadata-Version: 2.2
Name: godrive
Version: 1.0.3
Summary: A CLI tool to upload files and directories to Google Drive.
Home-page: https://github.com/yourusername/godrive
Author: Your Name
Author-email: Rohan Yadav <rohanbhatotiya@gmail.com>
License: MIT License
Keywords: google-drive,cli,upload
Classifier: Programming Language :: Python :: 3
Classifier: License :: OSI Approved :: MIT License
Classifier: Operating System :: OS Independent
Requires-Python: >=3.6
License-File: LICENSE
Requires-Dist: pydrive2
Requires-Dist: tqdm
Dynamic: author
Dynamic: home-page
Dynamic: requires-python
